nuclio/__init__.py
nuclio/event.py
nuclio/export.py
nuclio/request.py
nuclio/templates/nuclio.tpl
nuclio-0.1.0.dist-info/METADATA
nuclio-0.1.0.dist-info/RECORD
nuclio-0.1.0.dist-info/WHEEL
nuclio-0.1.0.dist-info/entry_points.txt
nuclio-0.1.0.dist-info/top_level.txt
