Metadata-Version: 2.1
Name: nuclio
Version: 0.1.0
Summary: Convert Jupyter notebook to nuclio
Home-page: https://github.com/nuclio/nuclio-jupyter
Author: Miki Tebeka
Author-email: miki@353solutions.com
License: MIT
Platform: UNKNOWN
Classifier: Development Status :: 4 - Beta
Classifier: Intended Audience :: Developers
Classifier: License :: OSI Approved :: Apache Software License
Classifier: Operating System :: POSIX :: Linux
Classifier: Operating System :: Microsoft :: Windows
Classifier: Operating System :: MacOS
Classifier: Programming Language :: Python :: 3
Classifier: Programming Language :: Python :: 3.6
Classifier: Programming Language :: Python :: 3.7
Classifier: Programming Language :: Python
Classifier: Topic :: Software Development :: Libraries :: Python Modules
Classifier: Topic :: Software Development :: Libraries
Requires-Dist: ipython (>=6.4.0)
Requires-Dist: jupyter (>=1.0.0)
Requires-Dist: traitlets (>=4.3.2)
